mcp_panther/__init__.py
mcp_panther/__main__.py
mcp_panther/server.py
mcp_panther/panther_mcp_core/__init__.py
mcp_panther/panther_mcp_core/client.py
mcp_panther/panther_mcp_core/permissions.py
mcp_panther/panther_mcp_core/queries.py
mcp_panther/panther_mcp_core/utils.py
mcp_panther/panther_mcp_core/validators.py
mcp_panther/panther_mcp_core/prompts/__init__.py
mcp_panther/panther_mcp_core/prompts/alert_triage.py
mcp_panther/panther_mcp_core/prompts/registry.py
mcp_panther/panther_mcp_core/prompts/reporting.py
mcp_panther/panther_mcp_core/resources/__init__.py
mcp_panther/panther_mcp_core/resources/config.py
mcp_panther/panther_mcp_core/resources/registry.py
mcp_panther/panther_mcp_core/tools/__init__.py
mcp_panther/panther_mcp_core/tools/alerts.py
mcp_panther/panther_mcp_core/tools/data_lake.py
mcp_panther/panther_mcp_core/tools/data_models.py
mcp_panther/panther_mcp_core/tools/detections.py
mcp_panther/panther_mcp_core/tools/global_helpers.py
mcp_panther/panther_mcp_core/tools/metrics.py
mcp_panther/panther_mcp_core/tools/permissions.py
mcp_panther/panther_mcp_core/tools/registry.py
mcp_panther/panther_mcp_core/tools/roles.py
mcp_panther/panther_mcp_core/tools/scheduled_queries.py
mcp_panther/panther_mcp_core/tools/schemas.py
mcp_panther/panther_mcp_core/tools/sources.py
mcp_panther/panther_mcp_core/tools/users.py
mseep_mcp_panther-2.0.3.dist-info/licenses/LICENSE
mseep_mcp_panther-2.0.3.dist-info/METADATA
mseep_mcp_panther-2.0.3.dist-info/WHEEL
mseep_mcp_panther-2.0.3.dist-info/entry_points.txt
mseep_mcp_panther-2.0.3.dist-info/top_level.txt
mseep_mcp_panther-2.0.3.dist-info/RECORD
